[{"category":"Drama","link_c":"/Drama","title":"Burning at Both Ends","link_s":"/Burning at Both Ends","img1":"https://www.themoviedb.org/t/p/w600_and_h900_bestv2/6pu1QbcaOWemDs7OUgnn1qnd3ag.jpg"},{"category":"Drama","link_c":"/Drama","title":"Love Joy","link_s":"/Love Joy","img1":"https://image.tmdb.org/t/p/w300//ls4ky4f4gIHngfr9RzYEVQ7I7lN.jpg"},{"category":"Drama","link_c":"/Drama","title":"Spider from the Attic","link_s":"/Spider from the Attic","img1":"https://m.media-amazon.com/images/M/MV5BYWUwZjc3MDAtMWE5Mi00NWViLWE5NmYtNDRkZmU1OGUzYjcyXkEyXkFqcGdeQXVyMjM4MTU4NjQ@._V1_FMjpg_UX1000_.jpg"},{"category":"Drama","link_c":"/Drama","title":"The Drummer","link_s":"/The Drummer","img1":"https://image.tmdb.org/t/p/w300//A0xQ5K1p4vvyNsuzz2MXM6BCjDF.jpg"},{"category":"Drama","link_c":"/Drama","title":"Celebrity Exorcism","link_s":"/Celebrity Exorcism","img1":"https://image.tmdb.org/t/p/w300//rIlS1bUei7HZjwEQZ58ARPesk5k.jpg"},{"category":"Drama","link_c":"/Drama","title":"Father Christmas Is Back","link_s":"/Father Christmas Is Back","img1":"https://image.tmdb.org/t/p/w300//mI6mFCO3lrJ4ovzwfmoLs58uhlK.jpg"},{"category":"Drama","link_c":"/Drama","title":"A Christmas Treasure","link_s":"/A Christmas Treasure","img1":"https://image.tmdb.org/t/p/w300//qTegIxclXI1P2nZBN3eo16YunBT.jpg"},{"category":"Drama","link_c":"/Drama","title":"Highway One","link_s":"/Highway One","img1":"https://image.tmdb.org/t/p/w300//g2SbkHvZ2NXtDzgn4VrakeSsMLu.jpg"},{"category":"Drama","link_c":"/Drama","title":"Knucks","link_s":"/Knucks","img1":"https://image.tmdb.org/t/p/w300//yUrKCrYEIoyIo5M3rcNozmyly8j.jpg"},{"category":"Drama","link_c":"/Drama","title":"The Souvenir: Part II","link_s":"/The Souvenir: Part II","img1":"https://www.themoviedb.org/t/p/w600_and_h900_bestv2/fYNvmZ1vW7bNcUhrAzYjUBgKJWP.jpg"},{"category":"Drama","link_c":"/Drama","title":"The Beta Test","link_s":"/The Beta Test","img1":"https://image.tmdb.org/t/p/w300//zZMebBIsNipjFhJFv0zjm0KQaBF.jpg"},{"category":"Drama","link_c":"/Drama","title":"A Rich Christmas","link_s":"/A Rich Christmas","img1":"https://www.themoviedb.org/t/p/w600_and_h900_bestv2/r3Vp9sIuBGsXBejpP15d994bMZX.jpg"}]